alltests.py
asp_selftest/__init__.py
asp_selftest/__main__.py
asp_selftest/arguments.py
asp_selftest/integration.py
asp_selftest/lib.py
asp_selftest/moretests.py
asp_selftest/session2.py
asp_selftest/plugins/__init__.py
asp_selftest/plugins/clingo_control_plugin.py
asp_selftest/plugins/clingo_defaults_plugin.py
asp_selftest/plugins/clingo_main_plugin.py
asp_selftest/plugins/clingo_sequencer_plugin.py
asp_selftest/plugins/clingo_syntaxerror_plugin.py
asp_selftest/plugins/clingoexitcodes.py
asp_selftest/plugins/compound_context_plugin.py
asp_selftest/plugins/insert_plugin_plugin.py
asp_selftest/plugins/messageparser.py
asp_selftest/plugins/misc.py
asp_selftest/plugins/source_plugin.py
asp_selftest/plugins/stdin_to_tempfile_plugin.py
asp_selftest/plugins/testrunner_plugin.py
asp_selftest/plugins/clingo_reify_plugin/__init__.py
asp_selftest/plugins/clingo_reify_plugin/asputil.py
asp_selftest/plugins/clingo_reify_plugin/clingo_reify_plugin.py
asp_selftest/plugins/clingo_reify_plugin/reify.lp
asp_selftest-0.1.5.dist-info/licenses/LICENSE
asp_selftest-0.1.5.dist-info/METADATA
asp_selftest-0.1.5.dist-info/WHEEL
asp_selftest-0.1.5.dist-info/entry_points.txt
asp_selftest-0.1.5.dist-info/top_level.txt
asp_selftest-0.1.5.dist-info/RECORD
