Metadata-Version: 2.4
Name: asp_selftest
Version: 0.1.5
Summary: A tool for running in-source unittests for Anwer Set Programming (ASP)
Author-email: Erik Groeneveld <ejgroene@ieee.org>
Project-URL: Homepage, https://github.com/ejgroene/asp-selftest
Project-URL: Issues, https://github.com/ejgroene/asp-selftest/issues
Classifier: Programming Language :: Python :: 3
Classifier: Programming Language :: ASP
Classifier: License :: OSI Approved :: GNU General Public License (GPL)
Classifier: Operating System :: OS Independent
Requires-Python: >=3.11
License-File: LICENSE
Requires-Dist: clingo>=5.8.0
Requires-Dist: selftest>=0.4.6
Requires-Dist: coverage
Dynamic: license-file
